scripts/__init__.py
scripts/relink.py
scripts/remove_meta.py
file_ops_suite-0.0.10.dist-info/LICENSE
file_ops_suite-0.0.10.dist-info/METADATA
file_ops_suite-0.0.10.dist-info/WHEEL
file_ops_suite-0.0.10.dist-info/entry_points.txt
file_ops_suite-0.0.10.dist-info/top_level.txt
file_ops_suite-0.0.10.dist-info/RECORD
